envirodataqc/QCconfig.py
envirodataqc/__init__.py
envirodataqc/dataqc.py
envirodataqc/wind.py
envirodataqc-0.3.1.dist-info/LICENSE
envirodataqc-0.3.1.dist-info/METADATA
envirodataqc-0.3.1.dist-info/WHEEL
envirodataqc-0.3.1.dist-info/top_level.txt
envirodataqc-0.3.1.dist-info/RECORD
