Metadata-Version: 2.1
Name: envirodataqc
Version: 0.3.1
Summary: Environmental data quality control
Home-page: https://github.com/chrisrycx/EnviroDataQC
Author: Chris Cox
Author-email: chrisrycx@gmail.com
License: UNKNOWN
Platform: UNKNOWN
Classifier: Programming Language :: Python :: 3
Classifier: License :: OSI Approved :: MIT License
Classifier: Operating System :: OS Independent
Requires-Python: >=3.8
License-File: LICENSE
Requires-Dist: pandas (==1.2.5)
